{
  "Class": "WARRIOR",
  "Spec": "Arms",
  "Updated": "2026-04-26",
  "Stats": {
    "Format": "ordered",
    "Ordered": [
      "Strength",
      "Critical Strike",
      "Haste",
      "Mastery",
      "Versatility"
    ],
    "Note": ""
  },
  "Gems": [
    {
      "Name": "Indecipherable Eversong Diamond",
      "Note": ""
    },
    {
      "Name": "Flawless Deadly Peridot",
      "Note": ""
    },
    {
      "Name": "Flawless Quick Garnet",
      "Note": ""
    }
  ],
  "Enchants": [
    {
      "Slot": "Weapon",
      "Enchant": "Enchant Weapon - Berserker's Rage"
    },
    {
      "Slot": "Helm",
      "Enchant": "Enchant Helm - Empowered Hex of Leeching"
    },
    {
      "Slot": "Shoulders",
      "Enchant": "Enchant Shoulders - Akil'zon's Swiftness"
    },
    {
      "Slot": "Chest",
      "Enchant": "Enchant Chest - Mark of the Worldsoul"
    },
    {
      "Slot": "Legs",
      "Enchant": "Blood Knight's Armor Kit"
    },
    {
      "Slot": "Boots",
      "Enchant": "Enchant Boots - Lynx's Dexterity"
    },
    {
      "Slot": "Rings",
      "Enchant": "Enchant Ring - Eyes of the Eagle"
    }
  ],
  "Consumables": {
    "Flask": "Flask of the Shattered Sun",
    "Food": "Harandar Celebration",
    "Potion": "Potion of Recklessness",
    "WeaponOil": "Thalassian Phoenix Oil",
    "AugRune": "Void-Touched Augment Rune"
  }
}